BayesianNetwork/__init__.py
BNetwork-0.1.dist-info/METADATA
BNetwork-0.1.dist-info/WHEEL
BNetwork-0.1.dist-info/top_level.txt
BNetwork-0.1.dist-info/RECORD
